codebehind/__init__.py
codebehind/authentication.py
codebehind/models.py
codebehind/serializers.py
codebehind/tests.py
codebehind/views.py
codebehind/migrations/0001_initial.py
codebehind/migrations/__init__.py
codebehind-1.4.17.dist-info/DESCRIPTION.rst
codebehind-1.4.17.dist-info/METADATA
codebehind-1.4.17.dist-info/RECORD
codebehind-1.4.17.dist-info/WHEEL
codebehind-1.4.17.dist-info/metadata.json
codebehind-1.4.17.dist-info/top_level.txt
