Metadata-Version: 2.0
Name: codebehind
Version: 1.4.17
Summary: Collection of magics.
Home-page: https://github.com/michaelhenry/codebehind/
Author: Michael Henry Pantaleon
Author-email: me@iamkel.net
License: MIT
Platform: UNKNOWN
Classifier: Environment :: Web Environment
Classifier: Framework :: Django
Classifier: Framework :: Django :: 1.9
Classifier: Intended Audience :: Developers
Classifier: Operating System :: OS Independent
Classifier: Programming Language :: Python
Classifier: Programming Language :: Python :: 3
Classifier: Programming Language :: Python :: 3.4
Classifier: Programming Language :: Python :: 3.5
Classifier: Topic :: Internet :: WWW/HTTP
Classifier: Topic :: Internet :: WWW/HTTP :: Dynamic Content
Requires-Dist: Django (>=1.9)
Requires-Dist: djangorestframework (>=3.5.3)
